[{"id": 1, "type": 2, "x1": -24, "y1": -103.25, "x2": -24, "y2": -29.75, "flipped": false, "leftExtended": false, "rightExtended": false}, {"id": 2, "type": 2, "x1": -24, "y1": -29.75, "x2": 42.5, "y2": -29.25, "flipped": false, "leftExtended": false, "rightExtended": false}, {"id": 3, "type": 2, "x1": 42.5, "y1": -29.25, "x2": 42.5, "y2": -103.25, "flipped": false, "leftExtended": false, "rightExtended": false}, {"id": 4, "type": 2, "x1": 42.5, "y1": -103.25, "x2": -24, "y2": -103.75, "flipped": false, "leftExtended": false, "rightExtended": false}, {"id": 5, "type": 2, "x1": -24, "y1": -103.25, "x2": -24, "y2": -29.75, "flipped": false, "leftExtended": false, "rightExtended": false}, {"id": 6, "type": 2, "x1": -24, "y1": -29.75, "x2": 42.5, "y2": -29.25, "flipped": false, "leftExtended": false, "rightExtended": false}, {"id": 7, "type": 2, "x1": 42.5, "y1": -29.25, "x2": 42.5, "y2": -103.25, "flipped": false, "leftExtended": false, "rightExtended": false}, {"id": 8, "type": 2, "x1": 42.5, "y1": -103.25, "x2": -24, "y2": -103.75, "flipped": false, "leftExtended": false, "rightExtended": false}, {"id": 9, "type": 2, "x1": -13.098814509295114, "y1": -86.84100642867801, "x2": -11.329864886041703, "y2": -86.84100642867801, "flipped": false, "leftExtended": false, "rightExtended": false}, {"id": 10, "type": 2, "x1": -11.329864886041703, "y1": -86.84100642867801, "x2": -9.466611181857964, "y2": -86.75550862185088, "flipped": false, "leftExtended": false, "rightExtended": false}, {"id": 11, "type": 2, "x1": -9.466611181857964, "y1": -86.75550862185088, "x2": -7.221857713830866, "y2": -86.61016235024475, "flipped": false, "leftExtended": false, "rightExtended": false}, {"id": 12, "type": 2, "x1": -7.221857713830866, "y1": -86.61016235024475, "x2": -0.6262517535131518, "y2": -86.37735182225447, "flipped": false, "leftExtended": false, "rightExtended": false}, {"id": 13, "type": 2, "x1": -0.6262517535131518, "y1": -86.37735182225447, "x2": 2.81379519323155, "y2": -86.51644820418153, "flipped": false, "leftExtended": false, "rightExtended": false}, {"id": 14, "type": 2, "x1": 2.81379519323155, "y1": -86.51644820418153, "x2": 5.905810510569916, "y2": -86.69931347835761, "flipped": false, "leftExtended": false, "rightExtended": false}, {"id": 15, "type": 2, "x1": 5.905810510569916, "y1": -86.69931347835761, "x2": 16.194299546912283, "y2": -87.12009323961756, "flipped": false, "leftExtended": false, "rightExtended": false}, {"id": 16, "type": 2, "x1": 16.194299546912283, "y1": -87.12009323961756, "x2": 17.495106535651924, "y2": -87.12186500316284, "flipped": false, "leftExtended": false, "rightExtended": false}, {"id": 17, "type": 2, "x1": 17.495106535651924, "y1": -87.12186500316284, "x2": 21.935547163199534, "y2": -87.12576079460247, "flipped": false, "leftExtended": false, "rightExtended": false}, {"id": 18, "type": 2, "x1": 11.125564091726302, "y1": -85.70103567098289, "x2": 10.87410050722054, "y2": -83.69061715684181, "flipped": false, "leftExtended": false, "rightExtended": false}, {"id": 19, "type": 2, "x1": 10.87410050722054, "y1": -83.69061715684181, "x2": 10.778543968918, "y2": -81.30131947213442, "flipped": false, "leftExtended": false, "rightExtended": false}, {"id": 20, "type": 2, "x1": 10.778543968918, "y1": -81.30131947213442, "x2": 10.540658778451952, "y2": -77.7478593426423, "flipped": false, "leftExtended": false, "rightExtended": false}, {"id": 21, "type": 2, "x1": 10.540658778451952, "y1": -77.7478593426423, "x2": 9.710389438103697, "y2": -68.67151614144815, "flipped": false, "leftExtended": false, "rightExtended": false}, {"id": 22, "type": 2, "x1": 9.710389438103697, "y1": -68.67151614144815, "x2": 9.194465959092, "y2": -64.11911982884239, "flipped": false, "leftExtended": false, "rightExtended": false}, {"id": 23, "type": 2, "x1": 9.194465959092, "y1": -64.11911982884239, "x2": 7.875875896811805, "y2": -52.670957535357566, "flipped": false, "leftExtended": false, "rightExtended": false}, {"id": 24, "type": 2, "x1": 7.875875896811805, "y1": -52.670957535357566, "x2": 7.7393108665334065, "y2": -51.20877266803629, "flipped": false, "leftExtended": false, "rightExtended": false}, {"id": 25, "type": 2, "x1": 7.7393108665334065, "y1": -51.20877266803629, "x2": 7.576798480502113, "y2": -48.9215867122303, "flipped": false, "leftExtended": false, "rightExtended": false}, {"id": 26, "type": 2, "x1": 7.576798480502113, "y1": -48.9215867122303, "x2": 7.642513682952908, "y2": -47.245129849509, "flipped": false, "leftExtended": false, "rightExtended": false}, {"id": 27, "type": 2, "x1": 7.642513682952908, "y1": -47.245129849509, "x2": 7.775990159089367, "y2": -45.29732426143765, "flipped": false, "leftExtended": false, "rightExtended": false}, {"id": 28, "type": 2, "x1": 7.775990159089367, "y1": -45.29732426143765, "x2": 7.9391059988757275, "y2": -43.80547791175948, "flipped": false, "leftExtended": false, "rightExtended": false}, {"id": 29, "type": 2, "x1": 7.9391059988757275, "y1": -43.80547791175948, "x2": 8.123616383614563, "y2": -42.50809219520568, "flipped": false, "leftExtended": false, "rightExtended": false}, {"id": 30, "type": 2, "x1": 8.123616383614563, "y1": -42.50809219520568, "x2": 8.410734255281156, "y2": -41.17280325215729, "flipped": false, "leftExtended": false, "rightExtended": false}, {"id": 31, "type": 2, "x1": 8.410734255281156, "y1": -41.17280325215729, "x2": 8.509215685262799, "y2": -39.82049208527985, "flipped": false, "leftExtended": false, "rightExtended": false}, {"id": 32, "type": 2, "x1": 8.509215685262799, "y1": -39.82049208527985, "x2": 8.542994815746502, "y2": -38.31870598015949, "flipped": false, "leftExtended": false, "rightExtended": false}, {"id": 33, "type": 2, "x1": -14.808770645837804, "y1": -38.1072565372114, "x2": -13.197478978373628, "y2": -38.46916875351066, "flipped": false, "leftExtended": false, "rightExtended": false}, {"id": 34, "type": 2, "x1": -13.197478978373628, "y1": -38.46916875351066, "x2": -11.628919114761654, "y2": -38.531590702275146, "flipped": false, "leftExtended": false, "rightExtended": false}, {"id": 35, "type": 2, "x1": -11.628919114761654, "y1": -38.531590702275146, "x2": -9.248460107826258, "y2": -38.57528606641029, "flipped": false, "leftExtended": false, "rightExtended": false}, {"id": 36, "type": 2, "x1": -9.248460107826258, "y1": -38.57528606641029, "x2": -6.3851695073915975, "y2": -38.77686843495916, "flipped": false, "leftExtended": false, "rightExtended": false}, {"id": 37, "type": 2, "x1": -6.3851695073915975, "y1": -38.77686843495916, "x2": 5.658605343354973, "y2": -39.350860077326296, "flipped": false, "leftExtended": false, "rightExtended": false}, {"id": 38, "type": 2, "x1": 5.658605343354973, "y1": -39.350860077326296, "x2": 8.324666649791984, "y2": -39.4052680494275, "flipped": false, "leftExtended": false, "rightExtended": false}, {"id": 39, "type": 2, "x1": 8.324666649791984, "y1": -39.4052680494275, "x2": 10.789394212087833, "y2": -39.528851436725475, "flipped": false, "leftExtended": false, "rightExtended": false}, {"id": 40, "type": 2, "x1": 10.789394212087833, "y1": -39.528851436725475, "x2": 22.22877648461383, "y2": -40.020381230691235, "flipped": false, "leftExtended": false, "rightExtended": false}, {"id": 41, "type": 2, "x1": 22.22877648461383, "y1": -40.020381230691235, "x2": 23.91894955137475, "y2": -40.06211153825942, "flipped": false, "leftExtended": false, "rightExtended": false}, {"id": 42, "type": 2, "x1": 23.91894955137475, "y1": -40.06211153825942, "x2": 29.152269463888175, "y2": -40.09890346429239, "flipped": false, "leftExtended": false, "rightExtended": false}, {"id": 43, "type": 2, "x1": 29.152269463888175, "y1": -40.09890346429239, "x2": 32.929848550324174, "y2": -40.10193343760649, "flipped": false, "leftExtended": false, "rightExtended": false}]